contactsoftware_functions-0.21.0.dist-info/licenses/LICENSE
csfunctions/__init__.py
csfunctions/config.py
csfunctions/devserver.py
csfunctions/handler.py
csfunctions/metadata.py
csfunctions/py.typed
csfunctions/request.py
csfunctions/response.py
csfunctions/util.py
csfunctions/actions/__init__.py
csfunctions/actions/abort_and_show_error.py
csfunctions/actions/base.py
csfunctions/actions/dummy.py
csfunctions/actions/start_workflow.py
csfunctions/events/__init__.py
csfunctions/events/base.py
csfunctions/events/bom_item_field_calculation.py
csfunctions/events/custom_operations.py
csfunctions/events/dialog_data.py
csfunctions/events/document_create_check.py
csfunctions/events/document_field_calculation.py
csfunctions/events/document_modify_check.py
csfunctions/events/document_release_check.py
csfunctions/events/document_released.py
csfunctions/events/dummy.py
csfunctions/events/engineering_change_release_check.py
csfunctions/events/engineering_change_released.py
csfunctions/events/engineering_change_status_change_check.py
csfunctions/events/engineering_change_status_changed.py
csfunctions/events/field_value_calculation.py
csfunctions/events/part_create_check.py
csfunctions/events/part_field_calculation.py
csfunctions/events/part_modify_check.py
csfunctions/events/part_release_check.py
csfunctions/events/part_released.py
csfunctions/events/workflow_task_trigger.py
csfunctions/objects/__init__.py
csfunctions/objects/base.py
csfunctions/objects/briefcase.py
csfunctions/objects/classification.py
csfunctions/objects/document.py
csfunctions/objects/engineering_change.py
csfunctions/objects/file.py
csfunctions/objects/part.py
csfunctions/objects/person.py
csfunctions/objects/workflow.py
csfunctions/service/__init__.py
csfunctions/service/base.py
csfunctions/service/file_upload.py
csfunctions/service/file_upload_schemas.py
csfunctions/service/numgen.py
csfunctions/tools/__init__.py
csfunctions/tools/write_schema.py
contactsoftware_functions-0.21.0.dist-info/METADATA
contactsoftware_functions-0.21.0.dist-info/WHEEL
contactsoftware_functions-0.21.0.dist-info/top_level.txt
contactsoftware_functions-0.21.0.dist-info/RECORD
