Metadata-Version: 2.4
Name: contactsoftware-functions
Version: 0.21.0
Summary: Library for creating Functions for CIM Database Cloud.
Author-email: Julian Alberts <jal@contact.de>, Jens Kürten <jku@contact.de>
License-Expression: MIT
Project-URL: Repository, https://github.com/cslab/functions-sdk-python
Project-URL: Documentation, https://cslab.github.io/functions-sdk-python/
Requires-Python: ~=3.10
License-File: LICENSE
Requires-Dist: requests<3,>=2.27.1
Requires-Dist: pydantic<3,>=2.3
Requires-Dist: pyyaml<7,>=6.0.2
Requires-Dist: werkzeug<4,>=3.1.3
Dynamic: license-file
